{
    "id": 8562822414,
    "name": "Tower of The Roof's Pique",
    "author": "JToH",
    "creators": ["xxDuzeRxx"],
    "verifier": "BoomSasok",
    "verification": "https://www.youtube.com/watch?v=9WkxSvUb10I",
    "percentToQualify": "100",
    "password": "Pit of Misery",
    "records": [
     {
            "user": "MonsterIsABlock",
            "link": "https://www.youtube.com/watch?v=FpuEAXvl4kk",
            "percent": 100,
            "hz": 90
        },
         {
            "user": "Henyxl",
            "link": "https://www.youtube.com/watch?v=i2eiNixDCWk",
            "percent": 100,
            "hz": 75
        },
            {
            "user": "Gehadimad",
            "link": "https://youtu.be/A7n3_xI7wrU",
            "percent": 100,
            "hz": 60
        },
         {
            "user": "MyntExists",
            "link": "https://www.youtube.com/watch?v=Z6QRrRKytZ0",
            "percent": 100,
            "hz": 75
        },
          {
            "user": "tinenderman",
            "link": "https://www.youtube.com/watch?v=310yQD2lBgc",
            "percent": 100,
            "hz": 75
        },
         {
            "user": "Conraderien",
            "link": "https://youtu.be/TIO-YIZl4T0?si=PyhxF4x4Su-gOoja",
            "percent": 100,
            "hz": 75
        },
          {
            "user": "llyaria",
            "link": "https://www.youtube.com/watch?v=JwuXmx6lRMM",
            "percent": 100,
            "hz": 90
        },
        {
            "user": "Sh4ngr",
            "link": "https://www.youtube.com/watch?v=oaMovoX2tXw",
            "percent": 100,
            "hz": 60
        },
        {
            "user": "wealithy",
            "link": "https://youtu.be/Ks5dbSInuxQ",
            "percent": 100,
            "hz": 75
        },
         {
            "user": "exexic",
            "link": "https://www.youtube.com/watch?v=HiqrER5bEsE",
            "percent": 100,
            "hz": 85
        },
         {
            "user": "myfrata",
            "link": "https://www.youtube.com/watch?v=lF3V5J2bzc8&t=257s",
            "percent": 100,
            "hz": 75
        },
          {
            "user": "Aimless",
            "link": "https://youtu.be/NmZyqPJ_9wM?list=UUo8wl3bJjAZGcP-XbaKJlbA",
            "percent": 100,
            "hz": 75
        },
          {
            "user": "Durukan2323",
            "link": "https://www.youtube.com/watch?v=3HvLq-o9v7w",
            "percent": 100,
            "hz": 75
        },
          {
            "user": "greenbean1421",
            "link": "https://www.youtube.com/watch?v=ALOb1jrOc4A",
            "percent": 100,
            "hz": 75
        },
          {
            "user": "Kampiel",
            "link": "https://www.youtube.com/watch?v=t-gcUKu7Nhk",
            "percent": 100,
            "hz": 75
        }
    ]
}
